i2cdevice/__init__.py
i2cdevice/adapter.py
i2cdevice-0.0.7.dist-info/LICENSE.txt
i2cdevice-0.0.7.dist-info/METADATA
i2cdevice-0.0.7.dist-info/WHEEL
i2cdevice-0.0.7.dist-info/top_level.txt
i2cdevice-0.0.7.dist-info/RECORD
